escalate/__init__.py
escalate/version.py
escalate-0.0.1.dist-info/LICENSE
escalate-0.0.1.dist-info/METADATA
escalate-0.0.1.dist-info/WHEEL
escalate-0.0.1.dist-info/entry_points.txt
escalate-0.0.1.dist-info/top_level.txt
escalate-0.0.1.dist-info/RECORD
