Metadata-Version: 2.1
Name: escalate
Version: 0.0.1
Summary: Escalate software CLI
Home-page: https://gitlab.com/eic/escalate/pyescalate
Author: Dmitry Romanov
Author-email: romanov@jlab.org
License: MIT
Platform: UNKNOWN
Classifier: Development Status :: 4 - Beta
Classifier: License :: OSI Approved :: MIT License
Classifier: Programming Language :: Python :: 2
Classifier: Programming Language :: Python :: 2.7
Classifier: Programming Language :: Python :: 3
Classifier: Programming Language :: Python :: 3.4
Classifier: Programming Language :: Python :: 3.6
Requires-Dist: click
Requires-Dist: appdirs
